Metadata-Version: 2.1
Name: amarna
Version: 0.1.5
Summary: Amarna is a static-analyzer for the Cairo programming language.
Home-page: https://github.com/crytic/amarna
Author: Trail of Bits
License: AGPL-3.0
Platform: UNKNOWN
Requires-Dist: lark (>=1.1.2)
Requires-Dist: pydot (>=1.4.2)
